.gitignore
.gitmodules
build.bat
CMakeLists.txt
Core/Core.vcxproj
Core/Core.vcxproj.filters
Core/src/bindings.cpp
Core/src/main.py
Core/src/Minimake/MSBuild/MSBuildEmitter.cpp
Core/src/Minimake/MSBuild/MSBuildEmitter.h
Core/src/Minimake/MSBuild/MSBuildManips.cpp
Core/src/Minimake/MSBuild/MSBuildManips.h
Core/src/Minimake/MSBuild/MSBuildParameter.cpp
Core/src/Minimake/MSBuild/MSBuildParameter.h
Core/src/Minimake/Parameters/Configuration.cpp
Core/src/Minimake/Parameters/Configuration.h
Core/src/Minimake/Parameters/Ide.cpp
Core/src/Minimake/Parameters/Ide.h
Core/src/Minimake/Parameters/OS.cpp
Core/src/Minimake/Parameters/OS.h
Core/src/Minimake/Parameters/Platform.cpp
Core/src/Minimake/Parameters/Platform.h
Core/src/Minimake/Projects/CppProject.cpp
Core/src/Minimake/Projects/CppProject.h
Core/src/Minimake/Projects/Project.cpp
Core/src/Minimake/Projects/Project.h
Core/src/Minimake.h
Core/src/pch.cpp
Core/src/pch.h
Core/src/run.bat
default_build.bat
LICENSE
minimake/__init__.py
Minimake.sln
PKG-INFO
pyproject.toml
README.md
setup.py
upload.bat
vendor/pybind11/.appveyor.yml
vendor/pybind11/.clang-format
vendor/pybind11/.clang-tidy
vendor/pybind11/.cmake-format.yaml
vendor/pybind11/.codespell-ignore-lines
vendor/pybind11/.gitattributes
vendor/pybind11/.github/CODEOWNERS
vendor/pybind11/.github/CONTRIBUTING.md
vendor/pybind11/.github/dependabot.yml
vendor/pybind11/.github/ISSUE_TEMPLATE/bug-report.yml
vendor/pybind11/.github/ISSUE_TEMPLATE/config.yml
vendor/pybind11/.github/labeler.yml
vendor/pybind11/.github/labeler_merged.yml
vendor/pybind11/.github/matchers/pylint.json
vendor/pybind11/.github/pull_request_template.md
vendor/pybind11/.github/workflows/ci.yml
vendor/pybind11/.github/workflows/configure.yml
vendor/pybind11/.github/workflows/format.yml
vendor/pybind11/.github/workflows/labeler.yml
vendor/pybind11/.github/workflows/pip.yml
vendor/pybind11/.github/workflows/upstream.yml
vendor/pybind11/.gitignore
vendor/pybind11/.pre-commit-config.yaml
minimake-1.0.1.dist-info/METADATA
minimake-1.0.1.dist-info/WHEEL
minimake-1.0.1.dist-info/licenses/LICENSE
minimake-1.0.1.dist-info/RECORD
