Metadata-Version: 2.2
Name: minimake
Version: 1.0.1
Summary: Multi Platform Project/Solution Builder
